topsis_ananya_102303594/__init__.py
topsis_ananya_102303594/topsis.py
topsis_ananya_102303594-0.2.dist-info/METADATA
topsis_ananya_102303594-0.2.dist-info/WHEEL
topsis_ananya_102303594-0.2.dist-info/entry_points.txt
topsis_ananya_102303594-0.2.dist-info/top_level.txt
topsis_ananya_102303594-0.2.dist-info/RECORD
