Metadata-Version: 2.4
Name: Topsis-Ananya-102303594
Version: 0.2
Summary: A Python package implementing the TOPSIS (Technique for Order Preference by Similarity to Ideal Solution) method
Author: Ananya Singh
Author-email: ananya@example.com
Classifier: Programming Language :: Python :: 3
Classifier: License :: OSI Approved :: MIT License
Classifier: Operating System :: OS Independent
Requires-Python: >=3.8
Requires-Dist: pandas
Requires-Dist: numpy
Dynamic: author
Dynamic: author-email
Dynamic: classifier
Dynamic: description
Dynamic: description-content-type
Dynamic: requires-dist
Dynamic: requires-python
Dynamic: summary
